{
  "name": "Final",
  "connectorType": "datagrid",
  "userId": null,
  "domoClientId": null,
  "domoClientSecret": "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",
  "additionalInfo": null,
  "reportLength": 0,
  "days": 7,
  "reports": null,
  "advancedReports": null,
  "guid": "58559add-0752-4abb-8a92-b946a8efc41f",
  "publishPrivate": true,
  "visibilityType": null,
  "parameters": null,
  "commands": null,
  "showAdvanced": false,
  "submittedVersion": 0,
  "submittedMajorVersion": 0,
  "publishedVersion": 0,
  "workbenchEnabled": false,
  "dataProviderCreated": false,
  "description": null,
  "tags": null,
  "successResponseDefinition": null,
  "errorResponseDefinition": null,
  "updateCode": false,
  "requestingCustomerId": null,
  "ownerId": null,
  "ownerCustomerId": null,
  "parentGuid": null,
  "testingProfiles": null,
  "visible": true
}